setup.py
client/__init__.py
client/add_contact.py
client/database.py
client/del_contact.py
client/main_window.py
client/main_window_conv.py
client/start_dialog.py
client/transport.py
client_messenger_from_dikson.egg-info/PKG-INFO
client_messenger_from_dikson.egg-info/SOURCES.txt
client_messenger_from_dikson.egg-info/dependency_links.txt
client_messenger_from_dikson.egg-info/requires.txt
client_messenger_from_dikson.egg-info/top_level.txt
common/__init__.py
common/decos.py
common/descryptors.py
common/errors.py
common/metaclasses.py
common/utils.py
common/variables.py
logs/__init__.py
logs/config_client_log.py
logs/config_server_log.py