Metadata-Version: 1.0
Name: client-messenger-from-dikson
Version: 0.0.1
Summary: client part of the messenger
Home-page: UNKNOWN
Author: Aleksey Ulyanov
Author-email: ulyanov-649@yandex.ru
License: UNKNOWN
Platform: UNKNOWN
